[
  {
    "id": "3067",
    "product_name": "ea",
    "company_name": "das Neves Silva Ltda.",
    "manufacturing_date": "2023-05-10",
    "expiration_date": "2043-07-14",
    "serial_number": "0244 1D62 0727 4ZV3 V7O5 1UJA ID33",
    "storage_instructions": "Illo inventore inventore ut quisquam accusantium deserunt ducimus. Doloribus odio blanditiis eligendi sit. Expedita placeat unde aperiam a magnam."
  },
  {
    "id": "2155",
    "product_name": "unde",
    "company_name": "das Neves Silva Ltda.",
    "manufacturing_date": "2023-10-29",
    "expiration_date": "2026-03-04",
    "serial_number": "NJ03 X614 4681 4MNB G0C8 46ZB 535S",
    "storage_instructions": "Soluta qui explicabo sequi dolore. Reiciendis tempora quis."
  },
  {
    "id": "9172",
    "product_name": "iure",
    "company_name": "das Neves Silva Ltda.",
    "manufacturing_date": "2023-05-23",
    "expiration_date": "2056-06-21",
    "serial_number": "4330 UOV5 9410 7CRL D9U9 R3B6 GO7K",
    "storage_instructions": "Totam dolor enim voluptate voluptas eius tempora. Accusantium illum asperiores fuga architecto amet hic mollitia. Iusto nisi nulla deserunt."
  },
  {
    "id": "4922",
    "product_name": "quo",
    "company_name": "Martins da Cruz - ME",
    "manufacturing_date": "2023-03-11",
    "expiration_date": "2024-01-26",
    "serial_number": "KD49 MDTI 6738 46G9 V2U6 KPUB 1K4Y",
    "storage_instructions": "Perspiciatis nemo commodi magnam magni ad. Impedit quia inventore quaerat vitae porro. Corporis rerum aliquam modi."
  },
  {
    "id": "8866",
    "product_name": "provident",
    "company_name": "Pinto Melo Ltda.",
    "manufacturing_date": "2023-01-24",
    "expiration_date": "2060-01-03",
    "serial_number": "WL63 GZQG 4370 8KQO I1R9 TF9O 778L",
    "storage_instructions": "Expedita eaque quaerat tempora quaerat eveniet tenetur magnam. Neque et adipisci ut vitae. Dolorem expedita saepe."
  }
]